changelog.md
TSDK/__init__.py
TSDK/api/base.py
TSDK/api/douyin/douyin.js
TSDK/api/douyin/h5.py
TSDK/api/douyin/readme.md
TSDK/api/douyin/strData_payload.png
TSDK/api/douyin/test.py
TSDK/api/eleme/h5.py
TSDK/api/meituan/h5.py
TSDK/api/taobao/h5.py
TSDK/api/taobao/open.py
TSDK/api/types/douyin.py
TSDK/api/types/eleme.py
TSDK/api/types/taobao.py
TSDK/bdms.js
TSDK/main.py
TSDK/tests/__init__.py
TSDK/tests/test_comment.py
tsdk-0.1.2.dist-info/entry_points.txt
tsdk-0.1.2.dist-info/METADATA
tsdk-0.1.2.dist-info/WHEEL
tsdk-0.1.2.dist-info/RECORD
